ezmsg/sigproc/__init__.py
ezmsg/sigproc/__version__.py
ezmsg/sigproc/activation.py
ezmsg/sigproc/adaptive_lattice_notch.py
ezmsg/sigproc/affinetransform.py
ezmsg/sigproc/aggregate.py
ezmsg/sigproc/bandpower.py
ezmsg/sigproc/base.py
ezmsg/sigproc/butterworthfilter.py
ezmsg/sigproc/butterworthzerophase.py
ezmsg/sigproc/cheby.py
ezmsg/sigproc/combfilter.py
ezmsg/sigproc/coordinatespaces.py
ezmsg/sigproc/decimate.py
ezmsg/sigproc/denormalize.py
ezmsg/sigproc/detrend.py
ezmsg/sigproc/diff.py
ezmsg/sigproc/downsample.py
ezmsg/sigproc/ewma.py
ezmsg/sigproc/ewmfilter.py
ezmsg/sigproc/extract_axis.py
ezmsg/sigproc/fbcca.py
ezmsg/sigproc/filter.py
ezmsg/sigproc/filterbank.py
ezmsg/sigproc/filterbankdesign.py
ezmsg/sigproc/fir_hilbert.py
ezmsg/sigproc/fir_pmc.py
ezmsg/sigproc/firfilter.py
ezmsg/sigproc/gaussiansmoothing.py
ezmsg/sigproc/kaiser.py
ezmsg/sigproc/linear.py
ezmsg/sigproc/messages.py
ezmsg/sigproc/quantize.py
ezmsg/sigproc/resample.py
ezmsg/sigproc/rollingscaler.py
ezmsg/sigproc/sampler.py
ezmsg/sigproc/scaler.py
ezmsg/sigproc/signalinjector.py
ezmsg/sigproc/singlebandpow.py
ezmsg/sigproc/slicer.py
ezmsg/sigproc/spectral.py
ezmsg/sigproc/spectrogram.py
ezmsg/sigproc/spectrum.py
ezmsg/sigproc/transpose.py
ezmsg/sigproc/wavelets.py
ezmsg/sigproc/window.py
ezmsg/sigproc/math/__init__.py
ezmsg/sigproc/math/abs.py
ezmsg/sigproc/math/add.py
ezmsg/sigproc/math/clip.py
ezmsg/sigproc/math/difference.py
ezmsg/sigproc/math/invert.py
ezmsg/sigproc/math/log.py
ezmsg/sigproc/math/pow.py
ezmsg/sigproc/math/scale.py
ezmsg/sigproc/util/__init__.py
ezmsg/sigproc/util/asio.py
ezmsg/sigproc/util/axisarray_buffer.py
ezmsg/sigproc/util/buffer.py
ezmsg/sigproc/util/message.py
ezmsg/sigproc/util/profile.py
ezmsg/sigproc/util/sparse.py
ezmsg/sigproc/util/typeresolution.py
ezmsg_sigproc-2.11.0.dist-info/METADATA
ezmsg_sigproc-2.11.0.dist-info/WHEEL
ezmsg_sigproc-2.11.0.dist-info/licenses/LICENSE
ezmsg_sigproc-2.11.0.dist-info/RECORD
