Metadata-Version: 2.4
Name: ezmsg-sigproc
Version: 2.11.0
Summary: Timeseries signal processing implementations in ezmsg
Author-email: Griffin Milsap <griffin.milsap@gmail.com>, Preston Peranich <pperanich@gmail.com>, Chadwick Boulay <chadwick.boulay@gmail.com>, Kyle McGraw <kmcgraw@blackrockneuro.com>
License-Expression: MIT
License-File: LICENSE
Requires-Python: >=3.10.15
Requires-Dist: array-api-compat>=1.11.1
Requires-Dist: ezmsg-baseproc>=1.1.0
Requires-Dist: ezmsg>=3.6.0
Requires-Dist: numba>=0.61.0
Requires-Dist: numpy>=1.26.0
Requires-Dist: pywavelets>=1.6.0
Requires-Dist: scipy>=1.13.1
Requires-Dist: sparse>=0.15.4
